auxilium/__init__.py
auxilium/bundles.py
auxilium/cli_tools.py
auxilium/rst_tools.py
auxilium/data/pkg.zip
auxilium/tools/__init__.py
auxilium/tools/deployment_tools.py
auxilium/tools/documentation_tools.py
auxilium/tools/setup_tools.py
auxilium/tools/test_tools.py
auxilium-0.1.4.data/scripts/auxilium
auxilium-0.1.4.data/scripts/multum-auxilium
pkg/__init__.py
pkg/dev.py
pkg/setup.py
pkg/test/__init__.py
pkg/test/unittests.py
test/__init__.py
test/unittests.py
auxilium-0.1.4.dist-info/LICENSE
auxilium-0.1.4.dist-info/METADATA
auxilium-0.1.4.dist-info/WHEEL
auxilium-0.1.4.dist-info/top_level.txt
auxilium-0.1.4.dist-info/RECORD
