Metadata-Version: 2.1
Name: auxilium
Version: 0.1.4
Summary: A Python project for an automated test and deploy toolkit - 100% reusable.
Home-page: https://github.com/sonntagsgesicht/auxilium
Author: sonntagsgesicht
Author-email: sonntagsgesicht@icloud.com
License: Apache License 2.0
Platform: any
Classifier: Development Status :: 3 - Alpha
Classifier: Intended Audience :: Education
Classifier: Intended Audience :: Developers
Classifier: License :: OSI Approved :: Apache Software License
Classifier: Operating System :: OS Independent
Classifier: Programming Language :: Python
Classifier: Programming Language :: Python :: 3
Classifier: Programming Language :: Python :: 3.5
Classifier: Programming Language :: Python :: 3.6
Classifier: Programming Language :: Python :: 3.7
Classifier: Programming Language :: Python :: 3.8
Classifier: Topic :: Education
Classifier: Topic :: Software Development
Requires-Dist: pylint
Requires-Dist: coverage
Requires-Dist: bandit
Requires-Dist: twine
Requires-Dist: sphinx
Requires-Dist: sphinx-rtd-theme
Requires-Dist: flake8
Requires-Dist: codecov
Requires-Dist: requests
